aiodown/__init__.py
aiodown/client.py
aiodown/errors/__init__.py
aiodown/errors/finished.py
aiodown/errors/paused.py
aiodown/errors/progress.py
aiodown/types/__init__.py
aiodown/types/download.py
aiodown-1.0.5.dist-info/LICENSE
aiodown-1.0.5.dist-info/METADATA
aiodown-1.0.5.dist-info/WHEEL
aiodown-1.0.5.dist-info/top_level.txt
aiodown-1.0.5.dist-info/RECORD
