Metadata-Version: 2.1
Name: aiodown
Version: 1.0.5
Summary: A fully async file downloader with httpx
Home-page: https://github.com/AmanoTeam/aiodown
Author: AmanoTeam
Author-email: contact@amanoteam.com
License: MIT
Download-URL: https://github.com/AmanoTeam/aiodown/releases/latest
Project-URL: Bug report, https://github.com/AmanoTeam/aiodown/issues
Project-URL: Donate, https://liberapay.com/AmanoTeam
Project-URL: Source, https://github.com/AmanoTeam/aiodown
Keywords: python,downloader,async,asyncio,httpx,file
Platform: UNKNOWN
Classifier: Development Status :: 4 - Beta
Classifier: License :: OSI Approved :: MIT License
Classifier: Operating System :: OS Independent
Classifier: Programming Language :: Python
Classifier: Programming Language :: Python :: 3
Classifier: Programming Language :: Python :: 3.8
Classifier: Programming Language :: Python :: 3.9
Classifier: Programming Language :: Python :: Implementation
Classifier: Programming Language :: Python :: Implementation :: CPython
Classifier: Programming Language :: Python :: Implementation :: PyPy
Classifier: Topic :: Internet
Requires-Python: >=3.8
Requires-Dist: async-files (>=0.4)
Requires-Dist: httpx[http2] (>=0.14)
Requires-Dist: humanize (>=3.2.0)
